repoze.tm2-2.2.0-nspkg.pth
repoze/tm/__init__.py
repoze/tm/tests.py
repoze.tm2-2.2.0.dist-info/LICENSE.txt
repoze.tm2-2.2.0.dist-info/METADATA
repoze.tm2-2.2.0.dist-info/WHEEL
repoze.tm2-2.2.0.dist-info/entry_points.txt
repoze.tm2-2.2.0.dist-info/namespace_packages.txt
repoze.tm2-2.2.0.dist-info/top_level.txt
repoze.tm2-2.2.0.dist-info/RECORD
